{
  "_class": "shapePath",
  "booleanOperation": -1,
  "clippingMaskMode": 0,
  "do_objectID": "AC5844B7-292F-4624-AEA4-053153993502",
  "edited": true,
  "exportOptions": {
    "_class": "exportOptions",
    "do_objectID": "ACB4716B-6862-4542-B401-C2C58383BA12",
    "exportFormats": [
    ],
    "includedLayerIds": [
    ],
    "layerOptions": 0,
    "shouldTrim": false
  },
  "frame": {
    "_class": "rect",
    "constrainProportions": false,
    "do_objectID": "497E469E-711F-4476-83AA-77839EEAA0B9",
    "height": 6.271484375,
    "width": 6.373046875,
    "x": 428.233130925,
    "y": 56.35546875
  },
  "hasClippingMask": false,
  "isClosed": true,
  "isFixedToViewport": false,
  "isFlippedHorizontal": false,
  "isFlippedVertical": false,
  "isLocked": false,
  "isVisible": true,
  "layerListExpandedType": 0,
  "name": "Path",
  "nameIsFixed": false,
  "pointRadiusBehaviour": 1,
  "points": [
    {
      "_class": "curvePoint",
      "cornerRadius": 0,
      "curveFrom": "{0.77689243027888444, 1}",
      "curveMode": 2,
      "curveTo": "{0.22310756972111553, 1}",
      "hasCurveFrom": true,
      "hasCurveTo": true,
      "point": "{0.49800796812749004, 1}"
    },
    {
      "_class": "curvePoint",
      "cornerRadius": 0,
      "curveFrom": "{1, 0.22267206477732793}",
      "curveMode": 2,
      "curveTo": "{1, 0.77732793522267207}",
      "hasCurveFrom": true,
      "hasCurveTo": true,
      "point": "{1, 0.50202429149797567}"
    },
    {
      "_class": "curvePoint",
      "cornerRadius": 0,
      "curveFrom": "{0.22310756972111553, 0}",
      "curveMode": 2,
      "curveTo": "{0.77689243027888444, 0}",
      "hasCurveFrom": true,
      "hasCurveTo": true,
      "point": "{0.49800796812749004, 0}"
    },
    {
      "_class": "curvePoint",
      "cornerRadius": 0,
      "curveFrom": "{0, 0.77732793522267207}",
      "curveMode": 2,
      "curveTo": "{0, 0.22267206477732793}",
      "hasCurveFrom": true,
      "hasCurveTo": true,
      "point": "{0, 0.50202429149797567}"
    }
  ],
  "resizingConstraint": 63,
  "resizingType": 0,
  "rotation": 0,
  "shouldBreakMaskChain": false,
  "style": {
    "_class": "style",
    "do_objectID": "C80098F2-DB2A-4FFD-AB3E-4344C7BA17B7",
    "endMarkerType": 0,
    "fills": [
      {
        "_class": "fill",
        "color": {
          "_class": "color",
          "alpha": 1,
          "blue": 0.7472,
          "green": 0.7551,
          "red": 0.2784
        },
        "fillType": 0,
        "isEnabled": true,
        "noiseIndex": 0,
        "noiseIntensity": 0,
        "patternFillType": 1,
        "patternTileScale": 1
      }
    ],
    "miterLimit": 10,
    "startMarkerType": 0,
    "textStyle": {
      "_class": "textStyle",
      "do_objectID": "9B484935-551D-4D2C-A623-A5E827CEDE5F",
      "encodedAttributes": {
        "MSAttributedStringColorAttribute": {
          "_class": "color",
          "alpha": 1,
          "blue": 0.2117647059,
          "green": 0.168627451,
          "red": 0.1294117647
        },
        "MSAttributedStringFontAttribute": {
          "_class": "fontDescriptor",
          "attributes": {
            "name": "SFProDisplay-Regular",
            "size": 52
          }
        },
        "kerning": -0.3151516,
        "paragraphStyle": {
          "_class": "paragraphStyle",
          "alignment": 0,
          "allowsDefaultTighteningForTruncation": 0,
          "maximumLineHeight": 56,
          "minimumLineHeight": 56
        }
      },
      "verticalAlignment": 0
    },
    "windingRule": 1
  }
}